senpkg/Analysis.py
senpkg/LandCoverCla.py
senpkg/LandCoverMod.py
senpkg/__init__.py
senpkg/base.py
Sentinel_imgpackage-0.0.9.dist-info/LICENSE
Sentinel_imgpackage-0.0.9.dist-info/METADATA
Sentinel_imgpackage-0.0.9.dist-info/WHEEL
Sentinel_imgpackage-0.0.9.dist-info/top_level.txt
Sentinel_imgpackage-0.0.9.dist-info/RECORD
